sparse_cdist.cpython-311-x86_64-linux-gnu.so
pytorch_sparse_addons/__init__.py
pytorch_sparse_addons/dist.py
pytorch_sparse_addons-0.1.9.dist-info/licenses/LICENSE
pytorch_sparse_addons-0.1.9.dist-info/METADATA
pytorch_sparse_addons-0.1.9.dist-info/WHEEL
pytorch_sparse_addons-0.1.9.dist-info/top_level.txt
pytorch_sparse_addons-0.1.9.dist-info/RECORD
